pyqt5ac.py
pyqt5ac-1.2.1.dist-info/LICENSE
pyqt5ac-1.2.1.dist-info/METADATA
pyqt5ac-1.2.1.dist-info/WHEEL
pyqt5ac-1.2.1.dist-info/entry_points.txt
pyqt5ac-1.2.1.dist-info/top_level.txt
pyqt5ac-1.2.1.dist-info/RECORD
