Metadata-Version: 2.1
Name: pyqt5ac
Version: 1.2.1
Summary: Python module to automatically compile UI and RC files in PyQt5 to Python files
Home-page: https://github.com/addisonElliott/pyqt5ac
Author: Addison Elliott
Author-email: addison.elliott@gmail.com
License: MIT License
Project-URL: Source, https://github.com/addisonElliott/pyqt5ac
Project-URL: Tracker, https://github.com/addisonElliott/pyqt5ac/issues
Keywords: pyqt pyqt5 qt qt5 qt auto compile generate ui rc pyuic5 pyrcc5 resource designer creator automatic
Platform: UNKNOWN
Classifier: License :: OSI Approved :: MIT License
Classifier: Topic :: Scientific/Engineering
Classifier: Programming Language :: Python
Classifier: Programming Language :: Python :: 3
Classifier: Programming Language :: Python :: 3.5
Classifier: Programming Language :: Python :: 3.6
Classifier: Programming Language :: Python :: 3.7
Classifier: Programming Language :: Python :: 3.8
Requires-Python: >=3
Provides-Extra: core
Provides-Extra: all
Provides-Extra: test
Provides-Extra: doc
Provides-Extra: dev
